codekoala/__init__.py
codekoala/cli.py
codekoala/config.py
codekoala/formatter.py
codekoala/git_integration.py
codekoala/koala_messages.py
codekoala/review_engine.py
codekoala/verify_ollama.py
codekoala-0.0.1.dist-info/METADATA
codekoala-0.0.1.dist-info/WHEEL
codekoala-0.0.1.dist-info/entry_points.txt
codekoala-0.0.1.dist-info/licenses/LICENSE
codekoala-0.0.1.dist-info/RECORD
