Metadata-Version: 2.4
Name: codekoala
Version: 0.0.1
Summary: Local-first LLM-powered code review and commit assistant
Project-URL: Homepage, https://github.com/pieter-ohearn/codekoala
Project-URL: Issues, https://github.com/pieter-ohearn/codekoala/issues
Author-email: Pieter OHearn <pieter.ohearn@gmail.com>
License: MIT
License-File: LICENSE
Keywords: code-review,commit-message,git,llm,ollama
Classifier: Development Status :: 3 - Alpha
Classifier: Intended Audience :: Developers
Classifier: License :: OSI Approved :: MIT License
Classifier: Operating System :: OS Independent
Classifier: Programming Language :: Python :: 3
Classifier: Programming Language :: Python :: 3.10
Classifier: Programming Language :: Python :: 3.11
Classifier: Topic :: Software Development :: Quality Assurance
Requires-Python: >=3.10
Requires-Dist: click>=8.1
Requires-Dist: gitpython>=3.1
Requires-Dist: ollama>=0.1.6
Requires-Dist: pyperclip>=1.8
Requires-Dist: rich>=13.0
